ipymagic/__init__.py
ipymagic/ipymagic.py
ipymagic/static/index.js
ipymagic-0.2.2.data/data/etc/jupyter/jupyter_notebook_config.d/ipymagic.json
ipymagic-0.2.2.data/data/etc/jupyter/nbconfig/notebook.d/ipymagic.json
ipymagic-0.2.2.data/data/share/jupyter/nbextensions/ipymagic/index.js
ipymagic-0.2.2.dist-info/LICENSE
ipymagic-0.2.2.dist-info/METADATA
ipymagic-0.2.2.dist-info/WHEEL
ipymagic-0.2.2.dist-info/top_level.txt
ipymagic-0.2.2.dist-info/RECORD
